{"nodes": [{"id": "c_users_shank_projects_github_pocketflow_lib_services_api_server_dart", "label": "api_server.dart", "file_type": "code", "source_file": "C:\\Users\\shank\\projects\\github\\PocketFlow\\lib\\services\\api_server.dart", "source_location": null}, {"id": "c_users_shank_projects_github_pocketflow_lib_services_api_server_dart_apiserver", "label": "ApiServer", "file_type": "code", "source_file": "C:\\Users\\shank\\projects\\github\\PocketFlow\\lib\\services\\api_server.dart", "source_location": null}, {"id": "c_users_shank_projects_github_pocketflow_lib_services_api_server_dart_cors", "label": "_cors", "file_type": "code", "source_file": "C:\\Users\\shank\\projects\\github\\PocketFlow\\lib\\services\\api_server.dart", "source_location": null}, {"id": "c_users_shank_projects_github_pocketflow_lib_services_api_server_dart_health", "label": "_health", "file_type": "code", "source_file": "C:\\Users\\shank\\projects\\github\\PocketFlow\\lib\\services\\api_server.dart", "source_location": null}, {"id": "c_users_shank_projects_github_pocketflow_lib_services_api_server_dart_response", "label": "Response", "file_type": "code", "source_file": "C:\\Users\\shank\\projects\\github\\PocketFlow\\lib\\services\\api_server.dart", "source_location": null}, {"id": "c_users_shank_projects_github_pocketflow_lib_services_api_server_dart_getsavedforgoal", "label": "_getSavedForGoal", "file_type": "code", "source_file": "C:\\Users\\shank\\projects\\github\\PocketFlow\\lib\\services\\api_server.dart", "source_location": null}, {"id": "dart_convert", "label": "dart:convert", "file_type": "code", "source_file": "C:\\Users\\shank\\projects\\github\\PocketFlow\\lib\\services\\api_server.dart", "source_location": null}, {"id": "dart_io", "label": "dart:io", "file_type": "code", "source_file": "C:\\Users\\shank\\projects\\github\\PocketFlow\\lib\\services\\api_server.dart", "source_location": null}, {"id": "package_shelf_shelf_dart", "label": "package:shelf/shelf.dart", "file_type": "code", "source_file": "C:\\Users\\shank\\projects\\github\\PocketFlow\\lib\\services\\api_server.dart", "source_location": null}, {"id": "package_shelf_shelf_io_dart", "label": "package:shelf/shelf_io.dart", "file_type": "code", "source_file": "C:\\Users\\shank\\projects\\github\\PocketFlow\\lib\\services\\api_server.dart", "source_location": null}, {"id": "package_shelf_router_shelf_router_dart", "label": "package:shelf_router/shelf_router.dart", "file_type": "code", "source_file": "C:\\Users\\shank\\projects\\github\\PocketFlow\\lib\\services\\api_server.dart", "source_location": null}, {"id": "db_database_dart", "label": "../db/database.dart", "file_type": "code", "source_file": "C:\\Users\\shank\\projects\\github\\PocketFlow\\lib\\services\\api_server.dart", "source_location": null}, {"id": "models_budget_dart", "label": "../models/budget.dart", "file_type": "code", "source_file": "C:\\Users\\shank\\projects\\github\\PocketFlow\\lib\\services\\api_server.dart", "source_location": null}, {"id": "models_savings_goal_dart", "label": "../models/savings_goal.dart", "file_type": "code", "source_file": "C:\\Users\\shank\\projects\\github\\PocketFlow\\lib\\services\\api_server.dart", "source_location": null}, {"id": "models_transaction_dart", "label": "../models/transaction.dart", "file_type": "code", "source_file": "C:\\Users\\shank\\projects\\github\\PocketFlow\\lib\\services\\api_server.dart", "source_location": null}], "edges": [{"source": "c_users_shank_projects_github_pocketflow_lib_services_api_server_dart", "target": "c_users_shank_projects_github_pocketflow_lib_services_api_server_dart_apiserver", "relation": "defines", "confidence": "EXTRACTED", "confidence_score": 1.0, "source_file": "C:\\Users\\shank\\projects\\github\\PocketFlow\\lib\\services\\api_server.dart", "source_location": null, "weight": 1.0}, {"source": "c_users_shank_projects_github_pocketflow_lib_services_api_server_dart", "target": "c_users_shank_projects_github_pocketflow_lib_services_api_server_dart_cors", "relation": "defines", "confidence": "EXTRACTED", "confidence_score": 1.0, "source_file": "C:\\Users\\shank\\projects\\github\\PocketFlow\\lib\\services\\api_server.dart", "source_location": null, "weight": 1.0}, {"source": "c_users_shank_projects_github_pocketflow_lib_services_api_server_dart", "target": "c_users_shank_projects_github_pocketflow_lib_services_api_server_dart_health", "relation": "defines", "confidence": "EXTRACTED", "confidence_score": 1.0, "source_file": "C:\\Users\\shank\\projects\\github\\PocketFlow\\lib\\services\\api_server.dart", "source_location": null, "weight": 1.0}, {"source": "c_users_shank_projects_github_pocketflow_lib_services_api_server_dart", "target": "c_users_shank_projects_github_pocketflow_lib_services_api_server_dart_response", "relation": "defines", "confidence": "EXTRACTED", "confidence_score": 1.0, "source_file": "C:\\Users\\shank\\projects\\github\\PocketFlow\\lib\\services\\api_server.dart", "source_location": null, "weight": 1.0}, {"source": "c_users_shank_projects_github_pocketflow_lib_services_api_server_dart", "target": "c_users_shank_projects_github_pocketflow_lib_services_api_server_dart_getsavedforgoal", "relation": "defines", "confidence": "EXTRACTED", "confidence_score": 1.0, "source_file": "C:\\Users\\shank\\projects\\github\\PocketFlow\\lib\\services\\api_server.dart", "source_location": null, "weight": 1.0}, {"source": "c_users_shank_projects_github_pocketflow_lib_services_api_server_dart", "target": "dart_convert", "relation": "imports", "confidence": "EXTRACTED", "confidence_score": 1.0, "source_file": "C:\\Users\\shank\\projects\\github\\PocketFlow\\lib\\services\\api_server.dart", "source_location": null, "weight": 1.0}, {"source": "c_users_shank_projects_github_pocketflow_lib_services_api_server_dart", "target": "dart_io", "relation": "imports", "confidence": "EXTRACTED", "confidence_score": 1.0, "source_file": "C:\\Users\\shank\\projects\\github\\PocketFlow\\lib\\services\\api_server.dart", "source_location": null, "weight": 1.0}, {"source": "c_users_shank_projects_github_pocketflow_lib_services_api_server_dart", "target": "package_shelf_shelf_dart", "relation": "imports", "confidence": "EXTRACTED", "confidence_score": 1.0, "source_file": "C:\\Users\\shank\\projects\\github\\PocketFlow\\lib\\services\\api_server.dart", "source_location": null, "weight": 1.0}, {"source": "c_users_shank_projects_github_pocketflow_lib_services_api_server_dart", "target": "package_shelf_shelf_io_dart", "relation": "imports", "confidence": "EXTRACTED", "confidence_score": 1.0, "source_file": "C:\\Users\\shank\\projects\\github\\PocketFlow\\lib\\services\\api_server.dart", "source_location": null, "weight": 1.0}, {"source": "c_users_shank_projects_github_pocketflow_lib_services_api_server_dart", "target": "package_shelf_router_shelf_router_dart", "relation": "imports", "confidence": "EXTRACTED", "confidence_score": 1.0, "source_file": "C:\\Users\\shank\\projects\\github\\PocketFlow\\lib\\services\\api_server.dart", "source_location": null, "weight": 1.0}, {"source": "c_users_shank_projects_github_pocketflow_lib_services_api_server_dart", "target": "db_database_dart", "relation": "imports", "confidence": "EXTRACTED", "confidence_score": 1.0, "source_file": "C:\\Users\\shank\\projects\\github\\PocketFlow\\lib\\services\\api_server.dart", "source_location": null, "weight": 1.0}, {"source": "c_users_shank_projects_github_pocketflow_lib_services_api_server_dart", "target": "models_budget_dart", "relation": "imports", "confidence": "EXTRACTED", "confidence_score": 1.0, "source_file": "C:\\Users\\shank\\projects\\github\\PocketFlow\\lib\\services\\api_server.dart", "source_location": null, "weight": 1.0}, {"source": "c_users_shank_projects_github_pocketflow_lib_services_api_server_dart", "target": "models_savings_goal_dart", "relation": "imports", "confidence": "EXTRACTED", "confidence_score": 1.0, "source_file": "C:\\Users\\shank\\projects\\github\\PocketFlow\\lib\\services\\api_server.dart", "source_location": null, "weight": 1.0}, {"source": "c_users_shank_projects_github_pocketflow_lib_services_api_server_dart", "target": "models_transaction_dart", "relation": "imports", "confidence": "EXTRACTED", "confidence_score": 1.0, "source_file": "C:\\Users\\shank\\projects\\github\\PocketFlow\\lib\\services\\api_server.dart", "source_location": null, "weight": 1.0}]}